aa_proxy_reg/__init__.py
aa_proxy_reg/admin.py
aa_proxy_reg/apps.py
aa_proxy_reg/forms.py
aa_proxy_reg/helpers.py
aa_proxy_reg/hooks.py
aa_proxy_reg/models.py
aa_proxy_reg/tasks.py
aa_proxy_reg/urls.py
aa_proxy_reg/views.py
aa_proxy_reg/migrations/0001_initial.py
aa_proxy_reg/migrations/0002_usersettings_api_backend.py
aa_proxy_reg/migrations/0003_alter_usersettings_options_and_more.py
aa_proxy_reg/migrations/0004_pluginsettings_delete_usersettings.py
aa_proxy_reg/migrations/0005_remove_pluginsettings_max_attempts_and_more.py
aa_proxy_reg/migrations/0006_remove_pluginsettings_enable_feature.py
aa_proxy_reg/migrations/__init__.py
aa_proxy_reg/static/aa_proxy_reg/images/notepad_1.png
aa_proxy_reg/static/aa_proxy_reg/images/notepad_2.png
aa_proxy_reg/static/aa_proxy_reg/images/notepad_3.png
aa_proxy_reg/static/aa_proxy_reg/images/notepad_4.png
aa_proxy_reg/static/aa_proxy_reg/images/notepad_5.png
aa_proxy_reg/static/aa_proxy_reg/images/notepad_7.jpg
aa_proxy_reg/static/aa_proxy_reg/images/start_icon.png
aa_proxy_reg/templates/aa_proxy_reg/main.html
aa_proxy_reg/templates/aa_proxy_reg/settings.html
aa_proxy_reg-0.21.dist-info/METADATA
aa_proxy_reg-0.21.dist-info/WHEEL
aa_proxy_reg-0.21.dist-info/top_level.txt
aa_proxy_reg-0.21.dist-info/RECORD
